MANIFEST.in
setup.py
jwplayer/__init__.py
jwplayer/base.html
jwplayer/global-site-footer.html
jwplayer/nav.html
jwplayer/search.html
jwplayer/site-header.html
jwplayer/site-secondary-header.html
jwplayer/css/mkdocs-jwplayer.css
jwplayer/css/mkdocs-jwplayer.min.css
jwplayer/img/jw-logo-mark-white.svg
jwplayer/img/jw-logo-text-white.svg
jwplayer/js/mkdocs-jwplayer.js
jwplayer/js/mkdocs-jwplayer.min.js
mkdocs_jwplayer.egg-info/PKG-INFO
mkdocs_jwplayer.egg-info/SOURCES.txt
mkdocs_jwplayer.egg-info/dependency_links.txt
mkdocs_jwplayer.egg-info/entry_points.txt
mkdocs_jwplayer.egg-info/not-zip-safe
mkdocs_jwplayer.egg-info/top_level.txt
site/__init__.py