Metadata-Version: 1.0
Name: mkdocs-jwplayer
Version: 0.0.2
Summary: JW Player theme for MkDocs
Home-page: https://github.com/jwplayer/mkdocs-jwplayer
Author: Matthew Martindale
Author-email: mmartindale@jwplayer.com
License: UNKNOWN
Platform: UNKNOWN
